colored_logging/__init__.py
colored_logging/colored_logging.py
colored_logging/version.txt
colored_logging-1.0.1.dist-info/LICENSE
colored_logging-1.0.1.dist-info/METADATA
colored_logging-1.0.1.dist-info/WHEEL
colored_logging-1.0.1.dist-info/top_level.txt
colored_logging-1.0.1.dist-info/RECORD
