Metadata-Version: 2.1
Name: colored_logging
Version: 1.0.1
Summary: formats logging messages in color
Author-email: "Gregory H. Halverson" <gregory.h.halverson@jpl.nasa.gov>
Classifier: Programming Language :: Python :: 3
Classifier: Operating System :: OS Independent
Requires-Python: >=3.10
License-File: LICENSE
Requires-Dist: termcolor
